logger/__init__.py
monitor_logger_common-0.1.0.dist-info/METADATA
monitor_logger_common-0.1.0.dist-info/WHEEL
monitor_logger_common-0.1.0.dist-info/top_level.txt
monitor_logger_common-0.1.0.dist-info/RECORD
