Metadata-Version: 2.1
Name: monitor-logger-common
Version: 0.1.0
Summary: Una librería para generar trazas en formato JSON
Author: Ricardo
Author-email: Ricardo Marzochi <ricardomarzochi@gmail.com>
License: MIT
Requires-Python: >=3.7
Requires-Dist: python-json-logger>=2.0.4
